shaolin/__init__.py
shaolin/colormaps.py
shaolin/dataframe.py
shaolin/dimension_mapper.py
shaolin/graph.py
shaolin/stream_plots.py
shaolin/utils.py
shaolin/version.py
shaolin-0.0.3.dist-info/METADATA
shaolin-0.0.3.dist-info/WHEEL
shaolin-0.0.3.dist-info/RECORD
